winstrument/__init__.py
winstrument/base_module.py
winstrument/cmdline.py
winstrument/db_connection.py
winstrument/settings_controller.py
winstrument/utils.py
winstrument/winstrument.py
winstrument/data/__init__.py
winstrument/data/module_message.py
winstrument/modules/__init__.py
winstrument/modules/com_hijack.py
winstrument/modules/dlls.py
winstrument/modules/file_rw.py
winstrument/modules/impersonate.py
winstrument/modules/metadata.toml
winstrument/modules/pipes.py
winstrument/modules/process.py
winstrument/modules/registry.py
winstrument/modules/socket.py
winstrument/modules/js/com_hijack.js
winstrument/modules/js/dlls.js
winstrument/modules/js/file_rw.js
winstrument/modules/js/impersonate.js
winstrument/modules/js/pipes.js
winstrument/modules/js/process.js
winstrument/modules/js/registry.js
winstrument/modules/js/socket.js
winstrument-0.1.1.dist-info/AUTHORS
winstrument-0.1.1.dist-info/LICENSE
winstrument-0.1.1.dist-info/METADATA
winstrument-0.1.1.dist-info/WHEEL
winstrument-0.1.1.dist-info/entry_points.txt
winstrument-0.1.1.dist-info/top_level.txt
winstrument-0.1.1.dist-info/RECORD
