Metadata-Version: 2.1
Name: winstrument
Version: 0.1.1
Summary: UNKNOWN
Home-page: https://github.com/nccgroup/Winstrument
Author: George Osterweil
Author-email: george@georgeosterweil.com
License: GPLv3
Keywords: winstrument instrumentation frida reverse engineering
Platform: UNKNOWN
Classifier: License :: OSI Approved :: GNU General Public License v3 (GPLv3)
Classifier: Operating System :: Microsoft :: Windows
Classifier: Programming Language :: Python :: 3.7
Classifier: Topic :: Security
Classifier: Topic :: System :: Operating System
Requires-Python: >=3.7.0
Requires-Dist: attrs (==19.1.0)
Requires-Dist: cmd2 (==0.9.15)
Requires-Dist: colorama (==0.4.1)
Requires-Dist: frida (<13.0.0,>=12.6.17)
Requires-Dist: frida-tools (==3.0.0)
Requires-Dist: pyperclip (==1.7.0)
Requires-Dist: pyreadline (==2.1)
Requires-Dist: pywin32 (>=224)
Requires-Dist: tabulate (==0.8.3)
Requires-Dist: toml (==0.10.0)
Requires-Dist: wcwidth (==0.1.7)
